af_client_sdk/__init__.py
af_client_sdk/client.py
af_client_sdk/types.py
af_client_sdk/utils.py
af_client_sdk-0.0.2.dist-info/licenses/LICENSE
af_client_sdk-0.0.2.dist-info/METADATA
af_client_sdk-0.0.2.dist-info/WHEEL
af_client_sdk-0.0.2.dist-info/top_level.txt
af_client_sdk-0.0.2.dist-info/RECORD
