Metadata-Version: 2.4
Name: af_client_sdk
Version: 0.0.2
Summary: ActiveFence Client SDK
Project-URL: repository, https://github.com/ActiveFence/ActiveFence-Guardrails-Python-SDK
Classifier: Programming Language :: Python :: 3
Classifier: Operating System :: OS Independent
License-File: LICENSE
Requires-Dist: aiohttp~=3.12
Requires-Dist: requests~=2.32
Provides-Extra: dev
Requires-Dist: pytest; extra == "dev"
Requires-Dist: pytest-asyncio; extra == "dev"
Requires-Dist: aioresponses; extra == "dev"
Requires-Dist: responses; extra == "dev"
Dynamic: license-file
